setup.py
Visualize/__init__.py
Visualize/facets.py
enso/__init__.py
enso/config.py
enso/utils.py
enso.egg-info/PKG-INFO
enso.egg-info/SOURCES.txt
enso.egg-info/dependency_links.txt
enso.egg-info/requires.txt
enso.egg-info/top_level.txt
enso/download/__init__.py
enso/download/__main__.py
enso/download/airline_sentiment.py
enso/download/brand_emotion.py
enso/download/chemical_disease_causes.py
enso/download/corporate_messaging.py
enso/download/customer_reviews.py
enso/download/detailed_emotion.py
enso/download/drug_experiences.py
enso/download/economy.py
enso/download/emotion.py
enso/download/global_warming.py
enso/download/movie_reviews.py
enso/download/mpqa.py
enso/download/new_years_resolutions.py
enso/download/political_tweet_classification.py
enso/download/political_tweets.py
enso/download/social_media_disasters.py
enso/download/sst_binary.py
enso/download/subjectivity.py
enso/experiment/NB.py
enso/experiment/__init__.py
enso/experiment/__main__.py
enso/experiment/grid_search.py
enso/experiment/logistic_regression.py
enso/experiment/naive_bayes.py
enso/experiment/random_forest.py
enso/experiment/svm.py
enso/featurize/__init__.py
enso/featurize/__main__.py
enso/featurize/indico_features.py
enso/featurize/spacy_features.py
enso/metrics/__init__.py
enso/metrics/basic_classification.py
enso/resample/__init__.py
enso/sample/__init__.py
enso/sample/kcenter_sampler.py
enso/sample/orthogonal_sampler.py
enso/sample/random_sampler.py
enso/visualize/__init__.py
enso/visualize/__main__.py
enso/visualize/facets.py