Metadata-Version: 1.0
Name: enso
Version: 0.1.2
Summary: Testing feature-sets and learning algorithms for transfer learning.
Home-page: UNKNOWN
Author: indico
Author-email: engineering@indico.io
License: UNKNOWN
Platform: UNKNOWN
